shaarpec/__init__.py
shaarpec/client.py
shaarpec/tasks.py
shaarpec/utils.py
shaarpec-2.5.0.dist-info/LICENSE
shaarpec-2.5.0.dist-info/METADATA
shaarpec-2.5.0.dist-info/WHEEL
shaarpec-2.5.0.dist-info/RECORD
