Metadata-Version: 2.1
Name: shaarpec
Version: 2.5.0
Summary: Client for SHAARPEC Analytics API.
Author: Erik G. Brandt
Author-email: erik.brandt@shaarpec.com
Requires-Python: >=3.10,<4.0
Classifier: Programming Language :: Python :: 3
Classifier: Programming Language :: Python :: 3.10
Classifier: Programming Language :: Python :: 3.11
Requires-Dist: Babel (>=2.12.1,<3.0.0)
Requires-Dist: anybadge (>=1.14.0,<2.0.0)
Requires-Dist: anyio (>=3.7.1,<4.0.0)
Requires-Dist: argon2-cffi (>=21.3.0,<22.0.0)
Requires-Dist: argon2-cffi-bindings (>=21.2.0,<22.0.0)
Requires-Dist: asttokens (>=2.2.1,<3.0.0)
Requires-Dist: attrs (>=23.1.0,<24.0.0)
Requires-Dist: backcall (>=0.2.0,<0.3.0)
Requires-Dist: background (>=0.2.1,<0.3.0)
Requires-Dist: beautifulsoup4 (>=4.12.2,<5.0.0)
Requires-Dist: bleach (>=6.0.0,<7.0.0)
Requires-Dist: certifi (>=2023.5.7,<2024.0.0)
Requires-Dist: cffi (>=1.15.1,<2.0.0)
Requires-Dist: charset-normalizer (>=3.1.0,<4.0.0)
Requires-Dist: click (>=8.1.3,<9.0.0)
Requires-Dist: debugpy (>=1.6.7,<2.0.0)
Requires-Dist: decorator (>=5.1.1,<6.0.0)
Requires-Dist: defusedxml (>=0.7.1,<0.8.0)
Requires-Dist: dill (>=0.3.6,<0.4.0)
Requires-Dist: ecdsa (>=0.18.0,<0.19.0)
Requires-Dist: entrypoints (>=0.4,<0.5)
Requires-Dist: executing (>=1.2.0,<2.0.0)
Requires-Dist: fastjsonschema (>=2.17.1,<3.0.0)
Requires-Dist: httpx (>=0.24.1,<0.25.0)
Requires-Dist: ipywidgets (>=8.0.7,<9.0.0)
Requires-Dist: jupyterlab-widgets (>=3.0.8,<4.0.0)
Requires-Dist: oidcish (>=1.0.1,<2.0.0)
Requires-Dist: pydantic (>=2.0.2,<3.0.0)
Requires-Dist: tqdm (>=4.65.0,<5.0.0)
